{
  "agent": "Rob-Agent",
  "updated": "2026-06-12T14:02:47.954Z",
  "source": "WWOZ Livewire",
  "date": "Friday, June 12, 2026",
  "shows": [
    {
      "time": "11:00am",
      "time_sort": 1100,
      "artist": "The New Orleans Rug Cutters",
      "url": "https://wwoz.org/events/1350271",
      "venue": "Bamboula's",
      "genre": "Other",
      "neighborhood": "French Quarter"
    },
    {
      "time": "11:00am",
      "time_sort": 1100,
      "artist": "Steamboat Stompers",
      "url": "https://wwoz.org/events/1349426",
      "venue": "Steamboat Natchez",
      "genre": "Other",
      "neighborhood": null
    },
    {
      "time": "12:00pm",
      "time_sort": 1200,
      "artist": "Royal Street Brass Band",
      "url": "https://wwoz.org/events/1355846",
      "venue": "Carousel Bar & Lounge at Hotel Monteleone",
      "genre": "Brass",
      "neighborhood": "French Quarter"
    },
    {
      "time": "12:00pm",
      "time_sort": 1200,
      "artist": "Salvador Avila Trio",
      "url": "https://wwoz.org/events/1353736",
      "venue": "San Lorenzo Restaurant at Hotel St. Vincent",
      "genre": "Jazz",
      "neighborhood": null
    },
    {
      "time": "12:30pm",
      "time_sort": 1230,
      "artist": "Richard \"Piano\" Scott",
      "url": "https://wwoz.org/events/1351136",
      "venue": "Fritzel's Jazz Club",
      "genre": "Jazz",
      "neighborhood": "French Quarter"
    },
    {
      "time": "1:00pm",
      "time_sort": 1300,
      "artist": "Victoria Amato + Ben Michaels",
      "url": "https://wwoz.org/events/1347421",
      "venue": "Pat O'Brien's",
      "genre": "Other",
      "neighborhood": null
    },
    {
      "time": "2:00pm",
      "time_sort": 1400,
      "artist": "Kid Merv & All That Jazz",
      "url": "https://wwoz.org/events/1352016",
      "venue": "Maison Bourbon Jazz Club",
      "genre": "Jazz",
      "neighborhood": null
    },
    {
      "time": "2:00pm",
      "time_sort": 1400,
      "artist": "Gallatin Street Fridays with The Marla Dixon Quintet",
      "url": "https://wwoz.org/events/1350516",
      "venue": "New Orleans Jazz Museum",
      "genre": "Jazz",
      "neighborhood": null
    },
    {
      "time": "2:00pm",
      "time_sort": 1400,
      "artist": "Paradise Jazz Band",
      "url": "https://wwoz.org/events/1356416",
      "venue": "Spotted Cat",
      "genre": "Jazz",
      "neighborhood": null
    },
    {
      "time": "2:00pm",
      "time_sort": 1400,
      "artist": "Steamboat Stompers",
      "url": "https://wwoz.org/events/1349611",
      "venue": "Steamboat Natchez",
      "genre": "Other",
      "neighborhood": null
    },
    {
      "time": "2:15pm",
      "time_sort": 1415,
      "artist": "Felipe Antonio Quarteto",
      "url": "https://wwoz.org/events/1350291",
      "venue": "Bamboula's",
      "genre": "Other",
      "neighborhood": "French Quarter"
    },
    {
      "time": "2:30pm",
      "time_sort": 1430,
      "artist": "Sam Friend Jazz Band",
      "url": "https://wwoz.org/events/1351041",
      "venue": "Fritzel's Jazz Club",
      "genre": "Jazz",
      "neighborhood": "French Quarter"
    },
    {
      "time": "3:00pm",
      "time_sort": 1500,
      "artist": "Big Joe Kennedy",
      "url": "https://wwoz.org/events/1351736",
      "venue": "21st Amendment",
      "genre": "Other",
      "neighborhood": "Central Business District"
    },
    {
      "time": "3:00pm",
      "time_sort": 1500,
      "artist": "Khris Royal Trio",
      "url": "https://wwoz.org/events/1348651",
      "venue": "Mahogany Jazz Hall",
      "genre": "Jazz",
      "neighborhood": null
    },
    {
      "time": "3:00pm",
      "time_sort": 1500,
      "artist": "Nola Sweethearts",
      "url": "https://wwoz.org/events/1353506",
      "venue": "Maison, The",
      "genre": "Other",
      "neighborhood": null
    },
    {
      "time": "3:00pm",
      "time_sort": 1500,
      "artist": "Saskia Walker Trio",
      "url": "https://wwoz.org/events/1352981",
      "venue": "New Orleans Jazz National Historical Park",
      "genre": "Jazz",
      "neighborhood": null
    },
    {
      "time": "4:00pm",
      "time_sort": 1600,
      "artist": "April Spain",
      "url": "https://wwoz.org/events/1352151",
      "venue": "Bourbon O Bar at The Bourbon Orleans Hotel",
      "genre": "Other",
      "neighborhood": "French Quarter"
    },
    {
      "time": "4:00pm",
      "time_sort": 1600,
      "artist": "Richard \"Piano\" Scott",
      "url": "https://wwoz.org/events/1355861",
      "venue": "Carousel Bar & Lounge at Hotel Monteleone",
      "genre": "Other",
      "neighborhood": "French Quarter"
    },
    {
      "time": "4:00pm",
      "time_sort": 1600,
      "artist": "Jass Hysteria",
      "url": "https://wwoz.org/events/1352291",
      "venue": "Favela Chic",
      "genre": "Other",
      "neighborhood": null
    },
    {
      "time": "5:00pm",
      "time_sort": 1700,
      "artist": "Lil Red & Big Bad",
      "url": "https://wwoz.org/events/1355141",
      "venue": "30/90",
      "genre": "Other",
      "neighborhood": "Mid-City"
    },
    {
      "time": "5:00pm",
      "time_sort": 1700,
      "artist": "Redline",
      "url": "https://wwoz.org/events/1357231",
      "venue": "Blue Crab Restaurant & Oyster Bar, The",
      "genre": "Other",
      "neighborhood": null
    },
    {
      "time": "5:00pm",
      "time_sort": 1700,
      "artist": "Shotgun Jazz Band",
      "url": "https://wwoz.org/events/1353531",
      "venue": "Maison, The",
      "genre": "Jazz",
      "neighborhood": null
    },
    {
      "time": "5:00pm",
      "time_sort": 1700,
      "artist": "Preservation All-Stars ft. Mark Braud",
      "url": "https://wwoz.org/events/1348026",
      "venue": "Preservation Hall",
      "genre": "Other",
      "neighborhood": null
    },
    {
      "time": "5:00pm",
      "time_sort": 1700,
      "artist": "Chris Vincent & the Raw Deals",
      "url": "https://wwoz.org/events/1352316",
      "venue": "Seithers Seafood (OUTDOORS)",
      "genre": "Other",
      "neighborhood": null
    },
    {
      "time": "6:00pm",
      "time_sort": 1800,
      "artist": "Tropical Weather",
      "url": "https://wwoz.org/events/1348761",
      "venue": "BMC",
      "genre": "Other",
      "neighborhood": "Uptown"
    },
    {
      "time": "6:00pm",
      "time_sort": 1800,
      "artist": "Eliza Sonneschien",
      "url": "https://wwoz.org/events/1354326",
      "venue": "Brutto Americano",
      "genre": "Other",
      "neighborhood": null
    },
    {
      "time": "6:00pm",
      "time_sort": 1800,
      "artist": "Dana Abbott Band",
      "url": "https://wwoz.org/events/1352691",
      "venue": "Café Negril",
      "genre": "Other",
      "neighborhood": "Marigny"
    },
    {
      "time": "6:00pm",
      "time_sort": 1800,
      "artist": "Michael Watson & The Alchemy",
      "url": "https://wwoz.org/events/1356186",
      "venue": "d.b.a.",
      "genre": "Other",
      "neighborhood": "Marigny"
    },
    {
      "time": "6:00pm",
      "time_sort": 1800,
      "artist": "Lange/Woodis Band",
      "url": "https://wwoz.org/events/1351066",
      "venue": "Fritzel's Jazz Club",
      "genre": "Jazz",
      "neighborhood": "French Quarter"
    },
    {
      "time": "6:00pm",
      "time_sort": 1800,
      "artist": "Adam Pearce",
      "url": "https://wwoz.org/events/1352361",
      "venue": "Hopedale Marina (OUTDOORS) - St. Bernard",
      "genre": "Other",
      "neighborhood": null
    },
    {
      "time": "6:00pm",
      "time_sort": 1800,
      "artist": "Jim Lockwood & Lisa Bittick-Lowe + Matt Hayden & Sydney Mcmath",
      "url": "https://wwoz.org/events/1347426",
      "venue": "Pat O'Brien's",
      "genre": "Other",
      "neighborhood": null
    },
    {
      "time": "6:00pm",
      "time_sort": 1800,
      "artist": "New Orleans Cottonmouth Kings",
      "url": "https://wwoz.org/events/1356401",
      "venue": "Spotted Cat",
      "genre": "Other",
      "neighborhood": null
    },
    {
      "time": "6:00pm",
      "time_sort": 1800,
      "artist": "Dukes of Dixieland",
      "url": "https://wwoz.org/events/1349726",
      "venue": "Steamboat Natchez",
      "genre": "Other",
      "neighborhood": null
    },
    {
      "time": "6:00pm",
      "time_sort": 1800,
      "artist": "Bad Penny Pleasuremakers",
      "url": "https://wwoz.org/events/1356006",
      "venue": "Three Muses",
      "genre": "Other",
      "neighborhood": null
    },
    {
      "time": "6:00pm",
      "time_sort": 1800,
      "artist": "Alex McMurray, Luke Allen & Arlo Allen",
      "url": "https://wwoz.org/events/1354396",
      "venue": "Tigermen Den",
      "genre": "Other",
      "neighborhood": null
    },
    {
      "time": "6:15pm",
      "time_sort": 1815,
      "artist": "Preservation All-Stars ft. Mark Braud",
      "url": "https://wwoz.org/events/1348051",
      "venue": "Preservation Hall",
      "genre": "Other",
      "neighborhood": null
    },
    {
      "time": "6:30pm",
      "time_sort": 1830,
      "artist": "Les Getrex & Creole Cookin'",
      "url": "https://wwoz.org/events/1350311",
      "venue": "Bamboula's",
      "genre": "Cajun",
      "neighborhood": "French Quarter"
    },
    {
      "time": "6:30pm",
      "time_sort": 1830,
      "artist": "Gumbo Funk",
      "url": "https://wwoz.org/events/1349006",
      "venue": "Three Maries Jazz Club at the Omni Royal Orleans",
      "genre": "Funk",
      "neighborhood": null
    },
    {
      "time": "7:00pm",
      "time_sort": 1900,
      "artist": "Willie Green III",
      "url": "https://wwoz.org/events/1348386",
      "venue": "Bacchanal (OUTDOORS)",
      "genre": "Other",
      "neighborhood": "Bywater"
    },
    {
      "time": "7:00pm",
      "time_sort": 1900,
      "artist": "Mark Barrett & The First Calls",
      "url": "https://wwoz.org/events/1352526",
      "venue": "B Mac's (OUTDOORS)",
      "genre": "Other",
      "neighborhood": null
    },
    {
      "time": "7:00pm",
      "time_sort": 1900,
      "artist": "Nell Simmons Bradley",
      "url": "https://wwoz.org/events/1353941",
      "venue": "Commons Club at Virgin Hotels New Orleans",
      "genre": "Other",
      "neighborhood": null
    },
    {
      "time": "7:00pm",
      "time_sort": 1900,
      "artist": "J.A.M. Brass Band",
      "url": "https://wwoz.org/events/1355046",
      "venue": "Favela Chic",
      "genre": "Brass",
      "neighborhood": null
    },
    {
      "time": "7:00pm",
      "time_sort": 1900,
      "artist": "Victor Campbell Son Del Sur",
      "url": "https://wwoz.org/events/1348476",
      "venue": "Mahogany Jazz Hall",
      "genre": "Jazz",
      "neighborhood": null
    },
    {
      "time": "7:30pm",
      "time_sort": 1930,
      "artist": "Trixie Minx's Burlesque Ballroom ft. Romy Kaye on Vocals",
      "url": "https://wwoz.org/events/1355736",
      "venue": "Jazz Playhouse",
      "genre": "Jazz",
      "neighborhood": null
    },
    {
      "time": "7:30pm",
      "time_sort": 1930,
      "artist": "Once : The Musical",
      "url": "https://wwoz.org/events/1346626",
      "venue": "Le Petit Théatre",
      "genre": "Other",
      "neighborhood": null
    },
    {
      "time": "7:30pm",
      "time_sort": 1930,
      "artist": "Matt Schofield",
      "url": "https://wwoz.org/events/1356036",
      "venue": "New Orleans Jazz & Blues Market",
      "genre": "Blues",
      "neighborhood": null
    },
    {
      "time": "7:30pm",
      "time_sort": 1930,
      "artist": "Preservation All-Stars ft. Mark Braud",
      "url": "https://wwoz.org/events/1348071",
      "venue": "Preservation Hall",
      "genre": "Other",
      "neighborhood": null
    },
    {
      "time": "7:30pm",
      "time_sort": 1930,
      "artist": "Astral Project",
      "url": "https://wwoz.org/events/1353151",
      "venue": "Snug Harbor",
      "genre": "Other",
      "neighborhood": null
    },
    {
      "time": "7:30pm",
      "time_sort": 1930,
      "artist": "Thomas Helton with Chris Alford, Boyanna Trayonova & More!",
      "url": "https://wwoz.org/events/1345396",
      "venue": "Zeitgeist Multi-Disciplinary Arts Center",
      "genre": "Other",
      "neighborhood": null
    },
    {
      "time": "8:00pm",
      "time_sort": 2000,
      "artist": "Dr. Sick & the Late Greats",
      "url": "https://wwoz.org/events/1351716",
      "venue": "21st Amendment",
      "genre": "Other",
      "neighborhood": "Central Business District"
    },
    {
      "time": "8:00pm",
      "time_sort": 2000,
      "artist": "The New Orleans Johnnys",
      "url": "https://wwoz.org/events/1356981",
      "venue": "30/90",
      "genre": "Other",
      "neighborhood": "Mid-City"
    },
    {
      "time": "8:00pm",
      "time_sort": 2000,
      "artist": "Bayou Blues Burlesque ft. The Delta Revues",
      "url": "https://wwoz.org/events/1357201",
      "venue": "AllWays Lounge",
      "genre": "Blues",
      "neighborhood": null
    },
    {
      "time": "8:00pm",
      "time_sort": 2000,
      "artist": "Solid Harmony ft. Peter Harris, Yolanda Robinson, Jolynda \"Kiki\" Chapman & More!",
      "url": "https://wwoz.org/events/1351411",
      "venue": "Bayou Bar at the Pontchartrain",
      "genre": "Other",
      "neighborhood": "Garden District"
    },
    {
      "time": "8:00pm",
      "time_sort": 2000,
      "artist": "Kid Merv & All That Jazz",
      "url": "https://wwoz.org/events/1351931",
      "venue": "Bourbon O Bar at The Bourbon Orleans Hotel",
      "genre": "Jazz",
      "neighborhood": "French Quarter"
    },
    {
      "time": "8:00pm",
      "time_sort": 2000,
      "artist": "T Marie & Bayou Juju",
      "url": "https://wwoz.org/events/1340016",
      "venue": "Buffa's",
      "genre": "Other",
      "neighborhood": "Marigny"
    },
    {
      "time": "8:00pm",
      "time_sort": 2000,
      "artist": "Mahmoud Chouki & Friends: Going Away Show!",
      "url": "https://wwoz.org/events/1354206",
      "venue": "Carrollton Station",
      "genre": "Other",
      "neighborhood": "Carrollton"
    },
    {
      "time": "8:00pm",
      "time_sort": 2000,
      "artist": "Jeremy Davenport",
      "url": "https://wwoz.org/events/1349336",
      "venue": "Davenport Lounge at The Ritz-Carlton",
      "genre": "Other",
      "neighborhood": "French Quarter"
    },
    {
      "time": "8:00pm",
      "time_sort": 2000,
      "artist": "DarkLounge Ministries",
      "url": "https://wwoz.org/events/1351546",
      "venue": "Holy Diver",
      "genre": "Other",
      "neighborhood": null
    },
    {
      "time": "8:00pm",
      "time_sort": 2000,
      "artist": "Feral House Cats",
      "url": "https://wwoz.org/events/1353541",
      "venue": "Maison, The",
      "genre": "Other",
      "neighborhood": null
    },
    {
      "time": "8:00pm",
      "time_sort": 2000,
      "artist": "Marsh Fire",
      "url": "https://wwoz.org/events/1343191",
      "venue": "True South",
      "genre": "Other",
      "neighborhood": null
    },
    {
      "time": "8:15pm",
      "time_sort": 2015,
      "artist": "The Leroy Marshall Band",
      "url": "https://wwoz.org/events/1346221",
      "venue": "Maison Bourbon Jazz Club",
      "genre": "Jazz",
      "neighborhood": null
    },
    {
      "time": "8:30pm",
      "time_sort": 2030,
      "artist": "John Lisi & Delta Funk",
      "url": "https://wwoz.org/events/1346136",
      "venue": "May Baily's Place",
      "genre": "Funk",
      "neighborhood": null
    },
    {
      "time": "8:30pm",
      "time_sort": 2030,
      "artist": "New Orleans Mystics",
      "url": "https://wwoz.org/events/1355371",
      "venue": "Mid-City Lanes Rock 'n' Bowl",
      "genre": "Rock",
      "neighborhood": null
    },
    {
      "time": "8:45pm",
      "time_sort": 2045,
      "artist": "Preservation All-Stars ft. Mark Braud",
      "url": "https://wwoz.org/events/1348091",
      "venue": "Preservation Hall",
      "genre": "Other",
      "neighborhood": null
    },
    {
      "time": "9:00pm",
      "time_sort": 2100,
      "artist": "Grape Candy/Bad Batch/Golden Hours",
      "url": "https://wwoz.org/events/1354506",
      "venue": "Bar Redux",
      "genre": "Other",
      "neighborhood": null
    },
    {
      "time": "9:00pm",
      "time_sort": 2100,
      "artist": "Cumbia Nasty Crew + Lapis",
      "url": "https://wwoz.org/events/1354606",
      "venue": "BJ's Lounge",
      "genre": "Other",
      "neighborhood": "Bywater"
    },
    {
      "time": "9:00pm",
      "time_sort": 2100,
      "artist": "Kat Kiley Experience",
      "url": "https://wwoz.org/events/1348766",
      "venue": "BMC",
      "genre": "Other",
      "neighborhood": "Uptown"
    },
    {
      "time": "9:00pm",
      "time_sort": 2100,
      "artist": "Big 6 Brass Band",
      "url": "https://wwoz.org/events/1355251",
      "venue": "Candlelight Lounge",
      "genre": "Brass",
      "neighborhood": null
    },
    {
      "time": "9:00pm",
      "time_sort": 2100,
      "artist": "The Nayo Jones Experience",
      "url": "https://wwoz.org/events/1355866",
      "venue": "Carousel Bar & Lounge at Hotel Monteleone",
      "genre": "Other",
      "neighborhood": "French Quarter"
    },
    {
      "time": "9:00pm",
      "time_sort": 2100,
      "artist": "Chorizo Funk DJ Set",
      "url": "https://wwoz.org/events/1353756",
      "venue": "Chapel Club at Hotel St. Vincent",
      "genre": "Electronic",
      "neighborhood": null
    },
    {
      "time": "9:00pm",
      "time_sort": 2100,
      "artist": "Tom Fitzpatrick with Sax & The City",
      "url": "https://wwoz.org/events/1352871",
      "venue": "Dos Jefes",
      "genre": "Other",
      "neighborhood": "Uptown"
    },
    {
      "time": "9:00pm",
      "time_sort": 2100,
      "artist": "Fritzel's All Star Band with Kevin Ray Clark",
      "url": "https://wwoz.org/events/1351086",
      "venue": "Fritzel's Jazz Club",
      "genre": "Jazz",
      "neighborhood": "French Quarter"
    },
    {
      "time": "9:00pm",
      "time_sort": 2100,
      "artist": "BassX & the Treme Brass Band",
      "url": "https://wwoz.org/events/1355531",
      "venue": "Gasa Gasa",
      "genre": "Brass",
      "neighborhood": "Uptown"
    },
    {
      "time": "9:00pm",
      "time_sort": 2100,
      "artist": "James Jordan Sextet ft. Zahria Sims",
      "url": "https://wwoz.org/events/1354281",
      "venue": "Good Measure at The Barnett",
      "genre": "Other",
      "neighborhood": null
    },
    {
      "time": "9:00pm",
      "time_sort": 2100,
      "artist": "Trixie Minx's Burlesque Ballroom ft. Romy Kaye on Vocals",
      "url": "https://wwoz.org/events/1355721",
      "venue": "Jazz Playhouse",
      "genre": "Jazz",
      "neighborhood": null
    },
    {
      "time": "9:00pm",
      "time_sort": 2100,
      "artist": "Nina Hungerland",
      "url": "https://wwoz.org/events/1355521",
      "venue": "Maple Leaf",
      "genre": "Other",
      "neighborhood": null
    },
    {
      "time": "9:00pm",
      "time_sort": 2100,
      "artist": "Country Night Dance Lessons ft. Rose Vaughn",
      "url": "https://wwoz.org/events/1356791",
      "venue": "No Dice",
      "genre": "Other",
      "neighborhood": null
    },
    {
      "time": "9:00pm",
      "time_sort": 2100,
      "artist": "High Gloss Presents: Corporate Pride ft. Otto Von Blotto, Virginia SlimJim, Nebula Omega & More!",
      "url": "https://wwoz.org/events/1351646",
      "venue": "Santos Bar",
      "genre": "Other",
      "neighborhood": null
    },
    {
      "time": "9:00pm",
      "time_sort": 2100,
      "artist": "Anaïs St. John",
      "url": "https://wwoz.org/events/1349021",
      "venue": "Three Maries Jazz Club at the Omni Royal Orleans",
      "genre": "Jazz",
      "neighborhood": null
    },
    {
      "time": "9:00pm",
      "time_sort": 2100,
      "artist": "Jelly Roll Stompers",
      "url": "https://wwoz.org/events/1356011",
      "venue": "Three Muses",
      "genre": "Other",
      "neighborhood": null
    },
    {
      "time": "9:00pm",
      "time_sort": 2100,
      "artist": "Free Fridays Concert Series ft. The Quickening + Sam Price & The True Believers",
      "url": "https://wwoz.org/events/1335661",
      "venue": "Tipitina's",
      "genre": "Other",
      "neighborhood": null
    },
    {
      "time": "9:30pm",
      "time_sort": 2130,
      "artist": "Tiffany Pollack",
      "url": "https://wwoz.org/events/1354896",
      "venue": "Double Dealer at Orpheum Theater",
      "genre": "Other",
      "neighborhood": "Central Business District"
    },
    {
      "time": "9:30pm",
      "time_sort": 2130,
      "artist": "Mahogany Hall Jazz Band ft. Mike Fulton with Midnight Burlesque",
      "url": "https://wwoz.org/events/1348691",
      "venue": "Mahogany Jazz Hall",
      "genre": "Jazz",
      "neighborhood": null
    },
    {
      "time": "9:30pm",
      "time_sort": 2130,
      "artist": "Astral Project",
      "url": "https://wwoz.org/events/1353146",
      "venue": "Snug Harbor",
      "genre": "Other",
      "neighborhood": null
    },
    {
      "time": "10:00pm",
      "time_sort": 2200,
      "artist": "Bettis & the 3rd Degree Brass Band",
      "url": "https://wwoz.org/events/1350331",
      "venue": "Bamboula's",
      "genre": "Brass",
      "neighborhood": "French Quarter"
    },
    {
      "time": "10:00pm",
      "time_sort": 2200,
      "artist": "Solid Harmony ft. Peter Harris, Yolanda Robinson, Jolynda \"Kiki\" Chapman & More!",
      "url": "https://wwoz.org/events/1351406",
      "venue": "Bayou Bar at the Pontchartrain",
      "genre": "Other",
      "neighborhood": "Garden District"
    },
    {
      "time": "10:00pm",
      "time_sort": 2200,
      "artist": "Kermit Ruffins & the BBQ Swingers",
      "url": "https://wwoz.org/events/1351201",
      "venue": "Blue Nile",
      "genre": "Jazz",
      "neighborhood": "Marigny"
    },
    {
      "time": "10:00pm",
      "time_sort": 2200,
      "artist": "Turn Up DJ Series with DJ FTK",
      "url": "https://wwoz.org/events/1351291",
      "venue": "Blue Nile - Balcony Room",
      "genre": "Electronic",
      "neighborhood": "Marigny"
    },
    {
      "time": "10:00pm",
      "time_sort": 2200,
      "artist": "Higher Heights",
      "url": "https://wwoz.org/events/1352711",
      "venue": "Café Negril",
      "genre": "Reggae",
      "neighborhood": "Marigny"
    },
    {
      "time": "10:00pm",
      "time_sort": 2200,
      "artist": "Troy Sawyer & The Elementz",
      "url": "https://wwoz.org/events/1356191",
      "venue": "d.b.a.",
      "genre": "Other",
      "neighborhood": "Marigny"
    },
    {
      "time": "10:00pm",
      "time_sort": 2200,
      "artist": "Hypno Nun",
      "url": "https://wwoz.org/events/1355061",
      "venue": "Favela Chic",
      "genre": "Other",
      "neighborhood": null
    },
    {
      "time": "10:00pm",
      "time_sort": 2200,
      "artist": "Margie Perez & the Diaspora",
      "url": "https://wwoz.org/events/1356146",
      "venue": "Headquarters by Nice Guys",
      "genre": "Other",
      "neighborhood": null
    },
    {
      "time": "10:00pm",
      "time_sort": 2200,
      "artist": "DJ Reverend Robert Sinewave",
      "url": "https://wwoz.org/events/1351556",
      "venue": "Holy Diver",
      "genre": "Electronic",
      "neighborhood": null
    },
    {
      "time": "10:00pm",
      "time_sort": 2200,
      "artist": "Vegas Cola Band",
      "url": "https://wwoz.org/events/1356396",
      "venue": "Spotted Cat",
      "genre": "Other",
      "neighborhood": null
    },
    {
      "time": "11:00pm",
      "time_sort": 2300,
      "artist": "Street Lyfe",
      "url": "https://wwoz.org/events/1356986",
      "venue": "30/90",
      "genre": "Other",
      "neighborhood": "Mid-City"
    },
    {
      "time": "11:00pm",
      "time_sort": 2300,
      "artist": "The Grace Manor Haints",
      "url": "https://wwoz.org/events/1346836",
      "venue": "Le Bon Temps Roulé",
      "genre": "Other",
      "neighborhood": null
    },
    {
      "time": "11:00pm",
      "time_sort": 2300,
      "artist": "DJ RQ Away",
      "url": "https://wwoz.org/events/1353546",
      "venue": "Maison, The",
      "genre": "Electronic",
      "neighborhood": null
    }
  ]
}
