{
  "agent": "Rob-Agent",
  "updated": "2026-07-13T23:41:42.380Z",
  "status": "ok",
  "location": "New Orleans, LA",
  "current": {
    "temp_f": 83,
    "feels_like_f": 96,
    "humidity": 72,
    "description": "Overcast",
    "code": "122",
    "emoji": "☁️",
    "wind_mph": 7,
    "wind_dir": "W",
    "visibility_miles": 16,
    "uv_index": 1
  },
  "forecast": [
    {
      "date": "2026-07-13",
      "label": "Mon, Jul 13",
      "high_f": 88,
      "low_f": 74,
      "description": "Patchy Rain",
      "emoji": "🌡️",
      "sunrise": "06:08 AM",
      "sunset": "08:03 PM",
      "avg_humidity": 90,
      "chance_of_rain": 91
    },
    {
      "date": "2026-07-14",
      "label": "Tue, Jul 14",
      "high_f": 77,
      "low_f": 72,
      "description": "Patchy Rain",
      "emoji": "🌡️",
      "sunrise": "06:09 AM",
      "sunset": "08:03 PM",
      "avg_humidity": 86,
      "chance_of_rain": 53
    },
    {
      "date": "2026-07-15",
      "label": "Wed, Jul 15",
      "high_f": 82,
      "low_f": 73,
      "description": "Partly Cloudy",
      "emoji": "⛅",
      "sunrise": "06:09 AM",
      "sunset": "08:03 PM",
      "avg_humidity": 77,
      "chance_of_rain": 50
    }
  ]
}